{
    "adapools": {
        "about": {
            "name": "Hellenic Alliance",
            "description_short": "We are Hellenic Cardano Stake pool operators, that strive to familiarize the Greek community with the Cardano Ecosystem.",
            "description_long": "We are all independent small businesses that operate Cardano Staking pool nodes for various reasons, but with a common goal: to bring Cardano's acceptance into the Greek society, on all levels. Academia, business, art, sports, entertainment etc.",
            "website": "https://cardano-community.gr",
            "url_png_icon_64x64": "http(s) url to pool icon; not animated; max 40kb",
            "url_png_logo": "http(s) url to pool logo; not animated; max 50kb",
            "social": {
                "twitter_handle": "hellenic_ada_alliance",
                "telegram_handle": "hellenic_ada_alliance",
                "facebook_handle": "",
                "youtube_handle": "",
                "twitch_handle": "",
                "discord_handle": "",
                "github_handle": ""
            },
            "types": {
                "charity": false,
                "business": false,
                "beneficial": false
            }
        },
        "members": {
            "0": {
                "pool_id": "89eba2781e5cd11ccda6be56503702a39e9941e522f04cd5bba22957",
                "member_since": "2020-07-29",
                "name": "[BSP] The Brothership Pool"
            },
            "1": {
                "pool_id": "a6d3691e1ff660bc6f6da75feea466a26b7f8a21c0f41d74940a7639",
                "member_since": "2020-07-30",
                "name": "[DOXA] DOXA"
            },
            "2": {
                "pool_id": "079c374160b0ae34a5a20b8e95a5b5c8766239b2984f13d7ab962791",
                "member_since": "2020-08-12",
                "name": "[SPEC] Spectrum Pool"
            },
            "3": {
                "pool_id": "b3291d8a4e04835ebaa71e0523b37abe64e4cd2eeea35c0886a2dd40",
                "member_since": "2020-10-08",
                "name": "[GRC1] Grc1Pool"
            },
            "4": {
                "pool_id": "5790d62ab1ba703e861fe800f9cefaaf1485c3ca42c6ba9ce74690a1",
                "member_since": "2020-11-02",
                "name": "[TTS17] Time To Stake"
            },            
            "5": {
                "pool_id": "c3cd2527a5f0b82a86ff69fdd5a3440dc51bcb957953ba19137738c0",
                "member_since": "2020-11-22",
                "name": "[SAPIO] SAPIO pool"
            },
            "6": {
                "pool_id": "a4b576a73fd6342c0ce8e44a040686b0e0ad54932df6724efd2364b3",
                "member_since": "2021-02-05",
                "name": "[ASKP] ADA Skepsis"
            },
            "7": {
                "pool_id": "f765c73fa3700f6fa735310ebc0255265613db23fd7bb14e8d84e795",
                "member_since": "2021-02-13",
                "name": "[HELAS] ELLADA"
            },
            "8": {
                "pool_id": "4d9333fceb79761fb826b22395c4bff84740fbfa8af232d6f6944eb7",
                "member_since": "2021-07-01",
                "name": "[FAM] Darkartopia Family"
            }
        }
    }
}